interfaces_to/__init__.py
interfaces_to/agent.py
interfaces_to/bases.py
interfaces_to/cli.py
interfaces_to/messages/__init__.py
interfaces_to/messages/cli.py
interfaces_to/messages/fastapi.py
interfaces_to/messages/gradio.py
interfaces_to/messages/ngrok.py
interfaces_to/messages/slack.py
interfaces_to/tools/airtable.py
interfaces_to/tools/notion.py
interfaces_to/tools/openai.py
interfaces_to/tools/peopledatalabs.py
interfaces_to/tools/self.py
interfaces_to/tools/slack.py
interfaces_to/tools/system.py
interfaces_to/utils.py
interfaces_to-0.2.30.dist-info/LICENSE
interfaces_to-0.2.30.dist-info/METADATA
interfaces_to-0.2.30.dist-info/WHEEL
interfaces_to-0.2.30.dist-info/entry_points.txt
interfaces_to-0.2.30.dist-info/RECORD
