Metadata-Version: 2.1
Name: interfaces-to
Version: 0.2.30
Summary: The quickest way to make Large Language Models do things.
Home-page: https://interfaces.to
License: MIT
Keywords: llm-agent,openai
Author: Blair Hudson
Author-email: blairhudson@users.noreply.github.com
Requires-Python: >=3.10,<4.0
Classifier: Development Status :: 3 - Alpha
Classifier: Intended Audience :: Developers
Classifier: License :: OSI Approved :: MIT License
Classifier: Programming Language :: Python :: 3
Classifier: Programming Language :: Python :: 3.10
Classifier: Programming Language :: Python :: 3.11
Classifier: Programming Language :: Python :: 3.12
Provides-Extra: fastapi
Provides-Extra: gradio
Provides-Extra: ngrok
Provides-Extra: notion
Provides-Extra: openai
Provides-Extra: peopledatalabs
Provides-Extra: slack
Requires-Dist: docstring-parser (>=0.16,<0.17)
Requires-Dist: fastapi (>=0.112.0) ; extra == "fastapi"
Requires-Dist: gradio (>=4.40.0) ; extra == "gradio"
Requires-Dist: ipywidgets (>=8.1.3) ; extra == "gradio"
Requires-Dist: ngrok (>=1.4.0) ; extra == "ngrok"
Requires-Dist: notion-client (>=2.2.1) ; extra == "notion"
Requires-Dist: openai (>=1.37.1) ; extra == "openai"
Requires-Dist: packaging (>=24.1,<25.0)
Requires-Dist: peopledatalabs (>=4.0.0) ; extra == "peopledatalabs"
Requires-Dist: pydantic (>=2.8.2,<3.0.0)
Requires-Dist: python-dotenv (>=1.0.1,<2.0.0)
Requires-Dist: requests (>=2.32.3,<3.0.0)
Requires-Dist: slack-sdk (>=3.31.0,<4.0.0) ; extra == "slack"
Requires-Dist: uvicorn (>=0.30.5) ; extra == "fastapi"
Project-URL: Documentation, https://interfaces.to/interfaces-to
Project-URL: Repository, https://github.com/interfaces-to/interfaces-to
